ID3classifier/__init__.py
ID3classifier/id3.py
ID3classifier-0.1.0.dist-info/LICENSE
ID3classifier-0.1.0.dist-info/METADATA
ID3classifier-0.1.0.dist-info/WHEEL
ID3classifier-0.1.0.dist-info/top_level.txt
ID3classifier-0.1.0.dist-info/RECORD
