Metadata-Version: 2.1
Name: ID3classifier
Version: 0.1.0
Summary: A simple ID3 decision tree implementation
Home-page: https://github.com/dingwalnitin/id3
Classifier: Programming Language :: Python :: 3
Classifier: License :: OSI Approved :: MIT License
Classifier: Operating System :: OS Independent
Requires-Python: >=3.6
License-File: LICENSE
Requires-Dist: numpy
Requires-Dist: pandas
Requires-Dist: scikit-learn
